blitzschnell/__init__.py
blitzschnell/py.typed
blitzschnell-0.1.1.dist-info/METADATA
blitzschnell-0.1.1.dist-info/WHEEL
blitzschnell-0.1.1.dist-info/licenses/LICENSE
blitzschnell-0.1.1.dist-info/RECORD
