Metadata-Version: 2.4
Name: blitzschnell
Version: 0.1.1
Summary: A fast Python library
Project-URL: Homepage, https://github.com/cosinusalpha/blitzschnell
Project-URL: Bug Tracker, https://github.com/cosinusalpha/blitzschnell/issues
Author-email: cosinusalpha <cvwhb6fjb@mozmail.com>
License: MIT
License-File: LICENSE
Classifier: License :: OSI Approved :: MIT License
Classifier: Programming Language :: Python :: 3
Classifier: Programming Language :: Python :: 3.9
Classifier: Programming Language :: Python :: 3.10
Classifier: Programming Language :: Python :: 3.11
Classifier: Programming Language :: Python :: 3.12
Classifier: Programming Language :: Python :: 3.13
Requires-Python: >=3.9
Provides-Extra: dev
Requires-Dist: mypy>=1.5.0; extra == 'dev'
Requires-Dist: ruff>=0.0.292; extra == 'dev'
Provides-Extra: plotting
Requires-Dist: matplotlib>=3.5.0; extra == 'plotting'
